anymotion_sdk/__init__.py
anymotion_sdk/_version.py
anymotion_sdk/auth.py
anymotion_sdk/client.py
anymotion_sdk/exceptions.py
anymotion_sdk/extras.py
anymotion_sdk/response.py
anymotion_sdk/session.py
anymotion_sdk/utils.py
anymotion_sdk-1.2.8.dist-info/LICENSE
anymotion_sdk-1.2.8.dist-info/WHEEL
anymotion_sdk-1.2.8.dist-info/METADATA
anymotion_sdk-1.2.8.dist-info/RECORD
