Metadata-Version: 2.1
Name: anymotion-sdk
Version: 1.2.8
Summary: AnyMotion SDK for Python
Home-page: https://github.com/nttpc/anymotion-python-sdk
License: MIT
Author: Yusuke Kumihashi
Author-email: y_kumiha@nttpc.co.jp
Requires-Python: >=3.6,<4.0
Classifier: License :: OSI Approved :: MIT License
Classifier: Programming Language :: Python :: 3
Classifier: Programming Language :: Python :: 3.10
Classifier: Programming Language :: Python :: 3.6
Classifier: Programming Language :: Python :: 3.7
Classifier: Programming Language :: Python :: 3.8
Classifier: Programming Language :: Python :: 3.9
Provides-Extra: cv
Requires-Dist: numpy (>=1.19,<2.0)
Requires-Dist: opencv-python (>=4.5,<5.0); extra == "cv"
Requires-Dist: requests (>=2.25,<3.0)
Project-URL: Repository, https://github.com/nttpc/anymotion-python-sdk
